DockerAnalyser-0.2.dist-info/DESCRIPTION.rst
DockerAnalyser-0.2.dist-info/METADATA
DockerAnalyser-0.2.dist-info/RECORD
DockerAnalyser-0.2.dist-info/WHEEL
DockerAnalyser-0.2.dist-info/entry_points.txt
DockerAnalyser-0.2.dist-info/metadata.json
DockerAnalyser-0.2.dist-info/top_level.txt
dockeranalyser/__init__.py
dockeranalyser/config.ini
dockeranalyser/constant.py
dockeranalyser/shell.py
dockeranalyser/core/__init__.py
dockeranalyser/core/monitor.py
dockeranalyser/core/mycompose.py
dockeranalyser/core/starter.py
dockeranalyser/core/utils.py
home/dido/.config/dockeranalyser/config.ini
