Metadata-Version: 2.0
Name: DockerAnalyser
Version: 0.2
Summary: Analyse Docker images.
Home-page: UNKNOWN
Author: UNKNOWN
Author-email: UNKNOWN
License: UNKNOWN
Platform: UNKNOWN
Requires-Dist: Click
Requires-Dist: GitPython
Requires-Dist: docker-compose
Requires-Dist: pika
Requires-Dist: six
